RcoreTutorialBookDisanbanFix1/README.md
RcoreTutorialBookDisanbanFix1/__init__.py
RcoreTutorialBookDisanbanFix1/__main__.py
RcoreTutorialBookDisanbanFix1/file.epub
RcoreTutorialBookDisanbanFix1/index.html
RcoreTutorialBookDisanbanFix1/css/__init__.py
RcoreTutorialBookDisanbanFix1/css/annotations.css
RcoreTutorialBookDisanbanFix1/css/main.css
RcoreTutorialBookDisanbanFix1/css/normalize.css
RcoreTutorialBookDisanbanFix1/css/popup.css
RcoreTutorialBookDisanbanFix1/font/__init__.py
RcoreTutorialBookDisanbanFix1/font/fontello.eot
RcoreTutorialBookDisanbanFix1/font/fontello.svg
RcoreTutorialBookDisanbanFix1/font/fontello.ttf
RcoreTutorialBookDisanbanFix1/font/fontello.woff
RcoreTutorialBookDisanbanFix1/img/__init__.py
RcoreTutorialBookDisanbanFix1/img/annotator-glyph-sprite.png
RcoreTutorialBookDisanbanFix1/img/annotator-icon-sprite.png
RcoreTutorialBookDisanbanFix1/img/apple-touch-icon.png
RcoreTutorialBookDisanbanFix1/img/cancelfullscreen.png
RcoreTutorialBookDisanbanFix1/img/close.png
RcoreTutorialBookDisanbanFix1/img/fullscreen.png
RcoreTutorialBookDisanbanFix1/img/loader.gif
RcoreTutorialBookDisanbanFix1/img/menu-icon.png
RcoreTutorialBookDisanbanFix1/img/save.png
RcoreTutorialBookDisanbanFix1/img/saved.png
RcoreTutorialBookDisanbanFix1/img/settings-s.png
RcoreTutorialBookDisanbanFix1/img/settings.png
RcoreTutorialBookDisanbanFix1/img/star.png
RcoreTutorialBookDisanbanFix1/js/__init__.py
RcoreTutorialBookDisanbanFix1/js/epub.js
RcoreTutorialBookDisanbanFix1/js/epub.min.js
RcoreTutorialBookDisanbanFix1/js/epub.min.map
RcoreTutorialBookDisanbanFix1/js/hooks.min.js
RcoreTutorialBookDisanbanFix1/js/hooks.min.map
RcoreTutorialBookDisanbanFix1/js/reader.js
RcoreTutorialBookDisanbanFix1/js/reader.js.map
RcoreTutorialBookDisanbanFix1/js/reader.min.js
RcoreTutorialBookDisanbanFix1/js/reader.min.map
RcoreTutorialBookDisanbanFix1/js/hooks/__init__.py
RcoreTutorialBookDisanbanFix1/js/hooks/extensions/__init__.py
RcoreTutorialBookDisanbanFix1/js/hooks/extensions/highlight.js
rcore_tutorial_book_disanban_fix1-2025.3.25.0.dist-info/METADATA
rcore_tutorial_book_disanban_fix1-2025.3.25.0.dist-info/WHEEL
rcore_tutorial_book_disanban_fix1-2025.3.25.0.dist-info/entry_points.txt
rcore_tutorial_book_disanban_fix1-2025.3.25.0.dist-info/top_level.txt
rcore_tutorial_book_disanban_fix1-2025.3.25.0.dist-info/RECORD
